{
  "creds": {
    "noiseKey": {
      "private": {
        "type": "Buffer",
        "data": "GMaFmVkBUHrlfeDHG4FtXKPGQ/KbAF9CVxEMKo6Qnmg="
      },
      "public": {
        "type": "Buffer",
        "data": "jz2RVG2HDpVuLj4Nje7cYwg2qbNB4J7XjLUkPjmekxI="
      }
    },
    "signedIdentityKey": {
      "private": {
        "type": "Buffer",
        "data": "aJLwQNU33TqDjZ6/E820qyvf9E+KpxEZFDN+6gFlZ3o="
      },
      "public": {
        "type": "Buffer",
        "data": "bgkLLqmNmCHc0tr/840AzzL2G6vI6psK03uiKbe0El4="
      }
    },
    "signedPreKey": {
      "keyPair": {
        "private": {
          "type": "Buffer",
          "data": "KBGgnu0WLv4/a8V5kOzCk8xGencKtnlbEzntz7nCfmc="
        },
        "public": {
          "type": "Buffer",
          "data": "jIN1ISjixzxDx0gaJQ9JhU5W6EYDqiFxMV+lj7jb5Fk="
        }
      },
      "signature": {
        "type": "Buffer",
        "data": "B96C8Rs0NFg4gJfdrD59XsrRQEysbMJIQOxqKtN35v0/8WowF1tOmSMOX8cPGyS/1H58Alr5UqFYwUQNGoqSjA=="
      },
      "keyId": 1
    },
    "registrationId": 5,
    "advSecretKey": "/tMwRyIMEON4xzxWK02ZaZi2kuRjkGQcnqjhnQUUP2Y=",
    "processedHistoryMessages": [
      {
        "key": {
          "remoteJid": "6289670432188@s.whatsapp.net",
          "fromMe": true,
          "id": "7A87878F02121AA66C856F4E8009362D"
        },
        "messageTimestamp": 1663640818
      },
      {
        "key": {
          "remoteJid": "6289670432188@s.whatsapp.net",
          "fromMe": true,
          "id": "BF1FF6B5B8FDA3094375ED294D7848C6"
        },
        "messageTimestamp": 1663640822
      },
      {
        "key": {
          "remoteJid": "6289670432188@s.whatsapp.net",
          "fromMe": true,
          "id": "AAF96A0ECF586AD07723AED4151DF072"
        },
        "messageTimestamp": 1663640875
      }
    ],
    "nextPreKeyId": 61,
    "firstUnuploadedPreKeyId": 61,
    "accountSettings": {
      "unarchiveChats": false
    },
    "account": {
      "details": "CJeJkJsCEOnJpJkGGAE=",
      "accountSignatureKey": "3YM8MdceglwSDn8PcshVQepeTfIdzY+uzxaYyHfemU8=",
      "accountSignature": "cci7fNEYjRiu5Gd2Cc7LWX5MIEC+0iwTDZJ+eZOqC8wUPPYHya420uv8w+GyykBbsH4WCHTH+pB9V5MpaVw8BQ==",
      "deviceSignature": "mm23rcfE7sEp9m1PpY9nkCveby1FmDKLbonmMcs3pl999CFFmUx/jeUWZBEAqpWszEGnG4xeIkKsFlIve/ThiA=="
    },
    "me": {
      "id": "6289670432188:19@s.whatsapp.net",
      "name": "B4KZONE"
    },
    "signalIdentities": [
      {
        "identifier": {
          "name": "6289670432188:19@s.whatsapp.net",
          "deviceId": 0
        },
        "identifierKey": {
          "type": "Buffer",
          "data": "Bd2DPDHXHoJcEg5/D3LIVUHqXk3yHc2Prs8WmMh33plP"
        }
      }
    ],
    "platform": "android",
    "lastAccountSyncTimestamp": 1663640813,
    "myAppStateKeyId": "AAAAAKO9"
  },
  "keys": {
    "preKeys": {
      "1": {
        "private": {
          "type": "Buffer",
          "data": "mLwZhZVLGYU8HXXDgXnyNzJOCvlYl2fuq2zeWW9V6nY="
        },
        "public": {
          "type": "Buffer",
          "data": "TOY+N6zhPjwIT0Lt95iUqkK7/mHQQbn/lf7xmZNc9Tg="
        }
      },
      "2": {
        "private": {
          "type": "Buffer",
          "data": "WP/ReYGrmaBUTNGcCprPA0s8BYEl/FphFoVoIv25f2c="
        },
        "public": {
          "type": "Buffer",
          "data": "aqXua7ZmLKuMxbM/xD9TWvNzxZGakMI6O+aYjiVx9VA="
        }
      },
      "3": {
        "private": {
          "type": "Buffer",
          "data": "iE2aeqWwPgiYKBJ3yuur3LRU5V0MtEUGxhb9G86gj08="
        },
        "public": {
          "type": "Buffer",
          "data": "hiAOziHykTrC8UWtadtkXvWx3mwV9HTCNugrZ0mgkhs="
        }
      },
      "4": {
        "private": {
          "type": "Buffer",
          "data": "GF5Hmb3PiS7Pvbko1sqxSwXedazHFscucMi2HbKt90g="
        },
        "public": {
          "type": "Buffer",
          "data": "m9ehrWj+QOYQwQ9bNETgUT9Fx764q/gtU5UsouWQAHQ="
        }
      },
      "5": {
        "private": {
          "type": "Buffer",
          "data": "CPtXW0AmIpWGKzmhUUQMJSZm6jbKeNdboccx5tIp/Vs="
        },
        "public": {
          "type": "Buffer",
          "data": "Eg9Yg5b597kPk1YXY/MA9n+r5RsxQorMMg6TBXUi1gQ="
        }
      },
      "6": {
        "private": {
          "type": "Buffer",
          "data": "aGgM4hk9E41rLHTY+VsZQbAQa+qSqxLBo5zY5pNFYFI="
        },
        "public": {
          "type": "Buffer",
          "data": "goiIGQeFAzL4MQkYol10+AsCpvfPaDPIWadUz4B2rxI="
        }
      },
      "7": {
        "private": {
          "type": "Buffer",
          "data": "SNcJLilZE0WOJWIUn8HcQTIcFFTJv5SA54PxfSHA2EI="
        },
        "public": {
          "type": "Buffer",
          "data": "RvStY/glc/cpPQq5qaKenK0x15IEIkuUj3cnhrXQLlo="
        }
      },
      "8": {
        "private": {
          "type": "Buffer",
          "data": "YP56mvp/XcytxOlfg+m1nTSYze6zjgWYjLaJeW0JiEU="
        },
        "public": {
          "type": "Buffer",
          "data": "wXuJTTzAZ1XwCZWcLKsJeFsD2+3MHriTFoW2HUw1ygI="
        }
      },
      "9": {
        "private": {
          "type": "Buffer",
          "data": "qPAmfQ+TPpSK9PUpEvxjX5bikWENXBsw+VlTaqEMAn0="
        },
        "public": {
          "type": "Buffer",
          "data": "BCynA4VvRucC5ksDz8+xYiDvb2dWLs9YKXxsIMWVsjM="
        }
      },
      "10": {
        "private": {
          "type": "Buffer",
          "data": "aBDrk5ndihBf2v+rn0ObM82Vr7lFmYX+yQsJgvSKolQ="
        },
        "public": {
          "type": "Buffer",
          "data": "KgA8aQK22e27kCm9EAWUjRVzyHbHJFRetH7qjynO9lc="
        }
      },
      "11": {
        "private": {
          "type": "Buffer",
          "data": "4KykqcEPKpMXFxIMpOOd2N2YlbCzBuOIDWv3EWcotG0="
        },
        "public": {
          "type": "Buffer",
          "data": "1ISJZSCl5lprIEsa+iOXZc0LfqPYIeEgTBowFIycCUs="
        }
      },
      "12": {
        "private": {
          "type": "Buffer",
          "data": "6J04mEC7uVNEdzaF0AnIhRzo9SKkm840zMD2xy/Y23c="
        },
        "public": {
          "type": "Buffer",
          "data": "mV/46ZesPdg0FimpBm/DXQziAWCpfSjkeNULNqdsCT4="
        }
      },
      "13": {
        "private": {
          "type": "Buffer",
          "data": "AMwHTnZ6D0dE2sQV0EeHd/RslvUH0pR1hzFOGD+nc28="
        },
        "public": {
          "type": "Buffer",
          "data": "fTWptCXeWGtG6gFg2M8tS3hF4LJRSK8oRIg7va571WY="
        }
      },
      "14": {
        "private": {
          "type": "Buffer",
          "data": "oF3cXjrRkVD1IRkg4KFF1voDetjY0lJvqeVIaebLpl0="
        },
        "public": {
          "type": "Buffer",
          "data": "B2mfCXsTYHvHBrQYgCokfGSo0g8OBQ8/rbZWFa6eeCA="
        }
      },
      "15": {
        "private": {
          "type": "Buffer",
          "data": "4KD/uY7MXGUHS6nmGb79ezRGJAfg9w2+VCdgXXaHKEo="
        },
        "public": {
          "type": "Buffer",
          "data": "WjsWy2P9j2nXjHp1JV2RoCjaZTORtD6NqvjWvkVCtUE="
        }
      },
      "16": {
        "private": {
          "type": "Buffer",
          "data": "2NDEvf56tiiCDn0cpnggw1XkIAAWMd6FkVvvC5Ni+08="
        },
        "public": {
          "type": "Buffer",
          "data": "0PwKa8pIfhYB5XtX8iT8A+4QTYk5E/nzQDsTJIWkwFM="
        }
      },
      "17": {
        "private": {
          "type": "Buffer",
          "data": "4FQNwMvgdT7Ji5asdW8W6533hbIkG1z+eGbvX/Pd+FU="
        },
        "public": {
          "type": "Buffer",
          "data": "jCa5f66jywMxKsZuAxOtewdeTXSa8nZZsedRtopAwHM="
        }
      },
      "18": {
        "private": {
          "type": "Buffer",
          "data": "oBXxISAX40nwaaSlEc0hzBhAd7sH1+5KB3Lwfcw1SGs="
        },
        "public": {
          "type": "Buffer",
          "data": "A7r9d2kcNbyxvxP904RYCtaHNxV+sBEygHuIGks/DjY="
        }
      },
      "19": {
        "private": {
          "type": "Buffer",
          "data": "iOm83vTUTsq1T79Ct9jHpuyJvZIyg41sEDkcJkYTplE="
        },
        "public": {
          "type": "Buffer",
          "data": "jHlfHipqZS9zU1wUSjijtcbYv2vL5L84L2mhK1Ll1yg="
        }
      },
      "20": {
        "private": {
          "type": "Buffer",
          "data": "GNNTHgtqvxPzzCunSumVu2MI9ahEhcTDPBZxC7+Sn2Y="
        },
        "public": {
          "type": "Buffer",
          "data": "duCiz2noy0OXipFJc2uk/o05lrpaUvypRrTAJvanIwM="
        }
      },
      "21": {
        "private": {
          "type": "Buffer",
          "data": "8F39GXBh+UQVHeGAPJJ9iLhvg3iVxG3h6kCm99q3kkI="
        },
        "public": {
          "type": "Buffer",
          "data": "fZ6apm70C4srqV1Jmeukxx93/jR8iBDEU3YtgjEsOUc="
        }
      },
      "22": {
        "private": {
          "type": "Buffer",
          "data": "4HrLIhL8LyZRwi+nXCC6hoMfQtYe442RFCotku2Ic1I="
        },
        "public": {
          "type": "Buffer",
          "data": "01XZoOG69vvwJx52KDeuft9WVxzSZnmkXIGGW5vrrCA="
        }
      },
      "23": {
        "private": {
          "type": "Buffer",
          "data": "YAV0v+R7RVmVyTE0pxMRCOq7D4OuJTwVFj6j36llnn4="
        },
        "public": {
          "type": "Buffer",
          "data": "hWEkd3iGG21uzD1H/XAPd1URy4Z73cmLIPN2XED1Ax8="
        }
      },
      "24": {
        "private": {
          "type": "Buffer",
          "data": "uB9bDD6nB9Dj34jo/hEf9v0YAaQmN2VUeJcgGnINrl4="
        },
        "public": {
          "type": "Buffer",
          "data": "M262dwiM+muYznsY5vQ55lES5du5RJHHd+aROl3eDG0="
        }
      },
      "25": {
        "private": {
          "type": "Buffer",
          "data": "eHZhW/olqb2L65PbfepJvV0jBUL3lBWOd70gQzXQt1o="
        },
        "public": {
          "type": "Buffer",
          "data": "XLk/LoV3GeaYxQjovESRp7n3olAdnDN+iRBZI87cHSs="
        }
      },
      "26": {
        "private": {
          "type": "Buffer",
          "data": "EJyC0vtORxXJWOmJdSt17nOadImDM56s+TUBruq6VXM="
        },
        "public": {
          "type": "Buffer",
          "data": "a0QCeLJju04wnuv6hjaGjtaaVD8F6UgzI4LkeOR9DSs="
        }
      },
      "27": {
        "private": {
          "type": "Buffer",
          "data": "oKmxD01m7hiM3LVgLeeJcoa3ByFLS0tq1e/nPtYl3U0="
        },
        "public": {
          "type": "Buffer",
          "data": "De8lcOF7xEuDJk00coeCD/y1e1Vlkfgpzcd5kaB4BW4="
        }
      },
      "28": {
        "private": {
          "type": "Buffer",
          "data": "mONFv5xO1KoaH5skr9p9Cyl+LvoOfyODybQGQNTieVo="
        },
        "public": {
          "type": "Buffer",
          "data": "qxTU2fV4ghyh7BZAZg5c7m9V/fRlqsUjbC5JygIQwAc="
        }
      },
      "29": {
        "private": {
          "type": "Buffer",
          "data": "8H1iDLJhpvjhlLxYbs5IlnHaXWXPtk6IMpmcyyhIVG4="
        },
        "public": {
          "type": "Buffer",
          "data": "7T9G9Qyfosrv+kdvddAR3KIzOQSXUSX7dTxjJNegXmI="
        }
      },
      "30": {
        "private": {
          "type": "Buffer",
          "data": "KDDi+JXOuG2xLWE1nYKDQYXIBvcICMSp9vCFX81E7FM="
        },
        "public": {
          "type": "Buffer",
          "data": "Zm/2RO1Kq2l1i0BNt7DX2uwRa1mE6WVh9rF6CuFv1xU="
        }
      },
      "31": {
        "private": {
          "type": "Buffer",
          "data": "EKJaEplZFYqgBRHHfIzASCRbtuabuz9npkReqCne4ko="
        },
        "public": {
          "type": "Buffer",
          "data": "HZDQ190MFkRSPC84qCW7jM4NUNwQ9rnx00tM3C10nxs="
        }
      },
      "32": {
        "private": {
          "type": "Buffer",
          "data": "uHD+NW6Kc/Jd/xAl/pCn0Ek77zUbYv/ofC5PunV/xFc="
        },
        "public": {
          "type": "Buffer",
          "data": "YKMLGBahvNUrM8EgSzGWC7zn0MV/Oe4uxRnWwOj832I="
        }
      },
      "33": {
        "private": {
          "type": "Buffer",
          "data": "SFKdSDsnKLc+2SmmS1DuUyB/5AJ9t8VHLlqo6CJ/yXY="
        },
        "public": {
          "type": "Buffer",
          "data": "qM36QjGllcS/UtFh0DWL/wXRKNMyjMuIRiaUAdjfw34="
        }
      },
      "34": {
        "private": {
          "type": "Buffer",
          "data": "uB0wGj2JK9iUQAWGRC7CdE184bdkIOWjRK88I9WfckQ="
        },
        "public": {
          "type": "Buffer",
          "data": "Fpwu7IM0lX6UXbxgh2sPAzItMKD9+tH3VW9PXgdgyAM="
        }
      },
      "35": {
        "private": {
          "type": "Buffer",
          "data": "OITsCMMijMn505VLIPiPzjLLatbu5aeWlAFtqn93FGs="
        },
        "public": {
          "type": "Buffer",
          "data": "WYCtcz0YCpdVfIeqlPuDVYQCdmDgjVzouqBqnDg5whw="
        }
      },
      "36": {
        "private": {
          "type": "Buffer",
          "data": "gHE9J0QIVjhdHD1dBhxVdCRRt1tfj4hTFX1ZscB/SnE="
        },
        "public": {
          "type": "Buffer",
          "data": "YXTFLyor4JSwoEa67G9N6sDS5ZpLnPoR0qc0DIRZZ1Y="
        }
      },
      "37": {
        "private": {
          "type": "Buffer",
          "data": "SOeW/feUK410PD0FfXt8JEEGXV1cQQLsw6P4aU+UkW0="
        },
        "public": {
          "type": "Buffer",
          "data": "hsvPLZcyLLyNns1V1YP25EN23DFI4P8/9rcVEvciV0M="
        }
      },
      "38": {
        "private": {
          "type": "Buffer",
          "data": "OAi/Aqvcq9BYBJOX6WUvwHDlqeWKWGnZA2OyOSvOqm4="
        },
        "public": {
          "type": "Buffer",
          "data": "NsW/oucmMhIB2hkb8Uy8bpg3ePABdXOOy/IVDFARPVQ="
        }
      },
      "39": {
        "private": {
          "type": "Buffer",
          "data": "KHabhztWqibk3jZlAmJQSEKBZqhmiVEmNr+lSnyLJmk="
        },
        "public": {
          "type": "Buffer",
          "data": "4sZ4fcDJ7qHNMsp3UkAUxMv12Y9N3dQ70gU+1Vdb8Tw="
        }
      },
      "40": {
        "private": {
          "type": "Buffer",
          "data": "+C0iLvDDfOBJSYndRjX1MG8OyValhTtanzCcXB6A3k0="
        },
        "public": {
          "type": "Buffer",
          "data": "6WLJ1mbpSeYVOzMwrki0+kW7W9xZjm/Zotloue5ztFY="
        }
      },
      "41": {
        "private": {
          "type": "Buffer",
          "data": "yC/1ziX5PnNlisTb+PhuVrj3uITj/hxqaGgo3EC7C1Q="
        },
        "public": {
          "type": "Buffer",
          "data": "IlZDLfMZqI4JNyns5gwPV5fnH2xvGUZZXbse2A91nE4="
        }
      },
      "42": {
        "private": {
          "type": "Buffer",
          "data": "cD+twOG4zb3o+au6jJBI1g2pWZRegLzx7qt15dPKdlU="
        },
        "public": {
          "type": "Buffer",
          "data": "lnbehO1wzwdF+IWqpu0NESelw0SnSD0Ngmh0KHyA1zk="
        }
      },
      "43": {
        "private": {
          "type": "Buffer",
          "data": "8M5oWFzrUj3fvyFPpOokiszTYEYiecbhfEqnM9wPFWU="
        },
        "public": {
          "type": "Buffer",
          "data": "q3cIY/Oe08coSigST60R/ty/DNHGIBDhw1Y2WATlhik="
        }
      },
      "44": {
        "private": {
          "type": "Buffer",
          "data": "uCgXkP33lxI6AwHIBPpSz/ZKB4EGC5wJBwozoJhanXA="
        },
        "public": {
          "type": "Buffer",
          "data": "Z5jEnEgmF2yS+fClX/QGidWzQvPQuTfPLiJOdlo9DQA="
        }
      },
      "45": {
        "private": {
          "type": "Buffer",
          "data": "iByOvF8wfcqQKepsGB6kf116M+p7VbnTv+j8qs/K2Es="
        },
        "public": {
          "type": "Buffer",
          "data": "bOa9gPDHBjcHDj55P60uiK4cuEJqoM2vzhJBcVuNI2Y="
        }
      },
      "46": {
        "private": {
          "type": "Buffer",
          "data": "8AkzG+nj0IGvySa1NmcYumGQQ/Qydjvfkki/0FYVqHQ="
        },
        "public": {
          "type": "Buffer",
          "data": "SwOfax+qodg9jKNocS7OJhuy+zgaKz7EWmIab4fCOTs="
        }
      },
      "47": {
        "private": {
          "type": "Buffer",
          "data": "UBweVjvNN9MS2EuPS16mCqlobDpL6casLAQY8S7q6kY="
        },
        "public": {
          "type": "Buffer",
          "data": "eA+cz6ZybD57ONhmOIuXFxjIqkrXbjj6G9bg5WzUf2A="
        }
      },
      "48": null,
      "49": {
        "private": {
          "type": "Buffer",
          "data": "0Fulm5hl5NG0oSK9tgi/Dv2TUPuTr7/f/iSH6ybNqEc="
        },
        "public": {
          "type": "Buffer",
          "data": "3JtKFtksJzxmTPhmeqFzyd4h4JoDMwibKu4lXn3KWmA="
        }
      },
      "50": {
        "private": {
          "type": "Buffer",
          "data": "+OZzV9QAyAD+TBOajin3UHdEJNtyR5OUQV03D+RirGg="
        },
        "public": {
          "type": "Buffer",
          "data": "PVCKBZ56euv+m2JEdsPi7RLhG+ZNnyhtBAzJyYs2wyo="
        }
      },
      "51": {
        "private": {
          "type": "Buffer",
          "data": "0H2zMkPH/Ov04WClt3KnC5zt9Omb1BdE+8yMTpJjT1Y="
        },
        "public": {
          "type": "Buffer",
          "data": "1xFP1NcjemKMf0KwYzgH7sB4Tiiv1kiQuug+XKx1dzI="
        }
      },
      "52": {
        "private": {
          "type": "Buffer",
          "data": "iF8OJdoXs03s+tBrP+OCbC8LwWp7KXvpftIm5y3gRGI="
        },
        "public": {
          "type": "Buffer",
          "data": "ybwERR9jR91EJuyBdE8zIvgqReCX3wrHXp1KHinvw2Y="
        }
      },
      "53": {
        "private": {
          "type": "Buffer",
          "data": "kHooHvk+ivuoRA3W/5wYxNkxqheGzAMxljR3m9puFGU="
        },
        "public": {
          "type": "Buffer",
          "data": "RYVQq4L08SPQREmsYkS39caHGYj4f0T5JZuEdu1T2ko="
        }
      },
      "54": {
        "private": {
          "type": "Buffer",
          "data": "qBz+D3Xh4wKIrGEap7M3ISR+bAFpBA0sM8kPMmmzO24="
        },
        "public": {
          "type": "Buffer",
          "data": "sFURvHecsqc9YJjUdRs7Ux2czdx2X4twQC1nH+Qo7hE="
        }
      },
      "55": {
        "private": {
          "type": "Buffer",
          "data": "OPVmS7aRMGaTdLjVS2InQH7qrO6G+T8Ca/i13wB25nE="
        },
        "public": {
          "type": "Buffer",
          "data": "H+mH4ZzvRTNkfirQ+IcxRPolRVJOnwr/9rGEO7BCsTg="
        }
      },
      "56": {
        "private": {
          "type": "Buffer",
          "data": "GL/1b8HUUwwgPUdIrRqemIgxDg0k/+0wVQgldJ7RCFU="
        },
        "public": {
          "type": "Buffer",
          "data": "Uz3xxljhS9qkJQPK0qAX+wem5bYiCSFyrshmnBvtUgA="
        }
      },
      "57": {
        "private": {
          "type": "Buffer",
          "data": "aLr/ZHQ8aWS81L+RnE3B90P8TO2wqZ0njIwZuDXWiEw="
        },
        "public": {
          "type": "Buffer",
          "data": "SKoRI+CSmRR7jGRYAaUG9cocymkDezwyTCM5paTB5GM="
        }
      },
      "58": {
        "private": {
          "type": "Buffer",
          "data": "ADbtfgQ4pDnHMfW4xOPdSFk1K160NVNchoKEOCWsRHc="
        },
        "public": {
          "type": "Buffer",
          "data": "By4SGPh44NrHizIrSIOEx9hh/366vGWgfqPTRTG7HhQ="
        }
      },
      "59": {
        "private": {
          "type": "Buffer",
          "data": "sFAKOEBIPoc71iHTqfw+Il7zRsk+mVMjJ+OpU975P2Y="
        },
        "public": {
          "type": "Buffer",
          "data": "5GD5cuiU576Ip8/mlxgd8RNKOUI/6TdhhCw0hUBZ4jk="
        }
      },
      "60": null
    },
    "sessions": {
      "6289670432188.0": {
        "_sessions": {
          "BdMTk84jR/xuFF6WXPNj8FBgF++dOK6hxkZUl1oih1Vh": {
            "registrationId": 2125563802,
            "currentRatchet": {
              "ephemeralKeyPair": {
                "pubKey": "BfRsc9MsJveC1+pth3LKbDV1ywghL/HtNOGjCzl7gG1c",
                "privKey": "KDEXLvZD/vy0upDkidjR3aVZHSK152hix5UXRU7yT0c="
              },
              "lastRemoteEphemeralKey": "BdBrktqQIAnApkhRYuC6/SEdfrxN5SKW8vW2biehaGlt",
              "previousCounter": 0,
              "rootKey": "LStUMNONO104U4Z1Zi4KWLAaHB0jtK4hez5kktFHmU4="
            },
            "indexInfo": {
              "baseKey": "BdMTk84jR/xuFF6WXPNj8FBgF++dOK6hxkZUl1oih1Vh",
              "baseKeyType": 2,
              "closed": -1,
              "used": 1663640874403,
              "created": 1663640813997,
              "remoteIdentityKey": "Bd2DPDHXHoJcEg5/D3LIVUHqXk3yHc2Prs8WmMh33plP"
            },
            "_chains": {
              "BZOZCq97JSBg5OHD7yXQzGZBR9HBpOdmQQXTvEKB0cB1": {
                "chainKey": {
                  "counter": 4
                },
                "chainType": 2,
                "messageKeys": {}
              },
              "BdBrktqQIAnApkhRYuC6/SEdfrxN5SKW8vW2biehaGlt": {
                "chainKey": {
                  "counter": 0,
                  "key": "irjzRlFGqHfk2lIaPQugdpLgBLnDLDfu28vbbzDbKrQ="
                },
                "chainType": 2,
                "messageKeys": {}
              },
              "BfRsc9MsJveC1+pth3LKbDV1ywghL/HtNOGjCzl7gG1c": {
                "chainKey": {
                  "counter": 3,
                  "key": "O+HKdOjmuGsKMKjSGWKR8xYKwXEP2JaSLPSGjYTF1FY="
                },
                "chainType": 1,
                "messageKeys": {}
              }
            }
          }
        },
        "version": "v1"
      },
      "6281236167286.0": {
        "_sessions": {
          "Bee+XvL8Ks2dJVdUGW6I7opK3f9YPNU4gTKp1O+btpZ8": {
            "registrationId": 431747412,
            "currentRatchet": {
              "ephemeralKeyPair": {
                "pubKey": "BY3bpe6yInucm8Kiw4EJAwa43gIDnc0Qt4OKuGy1tllw",
                "privKey": "aCeGwVDaXrqYS0TzfIhcormRZA1Yz5m3hZig2G2dzH8="
              },
              "lastRemoteEphemeralKey": "BT4X4yezXZXkxHR8B621cn4YSUxUgMOywqp5kMUhFUt+",
              "previousCounter": 0,
              "rootKey": "0whHZt/sXwDOU+t0tL1vtESWaA2qt1tkbOvimBpB33Y="
            },
            "indexInfo": {
              "baseKey": "Bee+XvL8Ks2dJVdUGW6I7opK3f9YPNU4gTKp1O+btpZ8",
              "baseKeyType": 2,
              "closed": -1,
              "used": 1663640926781,
              "created": 1663640830350,
              "remoteIdentityKey": "BQ4+9JffwP37/Qqyl5/eHPy8abLehK3K/Pq+BLL9VSlz"
            },
            "_chains": {
              "BdYQSyj2NYlRzt8Ja42Wzu6mnWGhxSeNNvpIQ1X5RcU/": {
                "chainKey": {
                  "counter": 1
                },
                "chainType": 2,
                "messageKeys": {}
              },
              "BVtfacUYxDntUSsodz9tnUzDPMcS8r+1DeI6caO/hqoU": {
                "chainKey": {
                  "counter": 0
                },
                "chainType": 2,
                "messageKeys": {}
              },
              "BUNPSEJAThsQ6h/6U7hGupk1bn6eDcerZn4BWYJwhnEC": {
                "chainKey": {
                  "counter": 1
                },
                "chainType": 2,
                "messageKeys": {}
              },
              "BT4X4yezXZXkxHR8B621cn4YSUxUgMOywqp5kMUhFUt+": {
                "chainKey": {
                  "counter": 0,
                  "key": "SuIdFtsd0nd8afYiZW+rM7DqsbBAQbgRLZ6hBzyhF3Q="
                },
                "chainType": 2,
                "messageKeys": {}
              },
              "BY3bpe6yInucm8Kiw4EJAwa43gIDnc0Qt4OKuGy1tllw": {
                "chainKey": {
                  "counter": 0,
                  "key": "9TnL8ej2A/MtW6HH4EBhXseK9YWMUMAkhG/LUfBJNp4="
                },
                "chainType": 1,
                "messageKeys": {}
              }
            }
          }
        },
        "version": "v1"
      },
      "62895382636517.0": {
        "_sessions": {
          "Bf99CHsZu2ua/cd2j2kWjoQcQ9UDiea0M431zco59kZj": {
            "registrationId": 838012053,
            "currentRatchet": {
              "ephemeralKeyPair": {
                "pubKey": "BcM5LoENd8GUJYjTtzo3R4A0R5GC3qTMjf+bjY25Czdc",
                "privKey": "oHvCrDuVNxLW3wI6Q1rUIlAJYwvyDRqkT8SfM/kY/08="
              },
              "lastRemoteEphemeralKey": "Bb/P8rJXXhII7tSjBwmaG6XR/tmzfjbSGiXvPICb/bdg",
              "previousCounter": 0,
              "rootKey": "EaI2x3Kq27/eNHd6NPKasVNbWETZUuh2XSAWH4aScNE="
            },
            "indexInfo": {
              "baseKey": "Bf99CHsZu2ua/cd2j2kWjoQcQ9UDiea0M431zco59kZj",
              "baseKeyType": 2,
              "closed": -1,
              "used": 1663640927813,
              "created": 1663640927813,
              "remoteIdentityKey": "BWVTXPcv58Z4CLZ5xRsNhj/hqlM/0puEokgzlXUOJyIg"
            },
            "_chains": {
              "Bb/P8rJXXhII7tSjBwmaG6XR/tmzfjbSGiXvPICb/bdg": {
                "chainKey": {
                  "counter": 0,
                  "key": "HqN7N4iMzbcSSGAXP9JEha0zdsWy31ioCx54+kXTiTQ="
                },
                "chainType": 2,
                "messageKeys": {}
              },
              "BcM5LoENd8GUJYjTtzo3R4A0R5GC3qTMjf+bjY25Czdc": {
                "chainKey": {
                  "counter": -1,
                  "key": "DbeDFLDv1zvfHIUBiEbwugBs/WWnNFFNGBQNgi2KMcA="
                },
                "chainType": 1,
                "messageKeys": {}
              }
            }
          }
        },
        "version": "v1"
      }
    },
    "appStateSyncKeys": {
      "AAAAAKPK": {
        "keyData": "5TXxv12VRiGsiKzqZ69qtjMnHQZGj8KXBUbDBL6rals=",
        "fingerprint": {
          "rawId": 593757328,
          "currentIndex": 2,
          "deviceIndexes": [
            0,
            1
          ]
        },
        "timestamp": "1663631591881"
      },
      "AAAAAKPD": {
        "keyData": "NseXLlYOHToIvfTrQkMFvB1ir3mSQvoXtY2ohB4oo/4=",
        "fingerprint": {
          "rawId": 593757316,
          "currentIndex": 1,
          "deviceIndexes": [
            0,
            1
          ]
        },
        "timestamp": "1663555413358"
      },
      "AAAAAKPH": {
        "keyData": "BfIwkbQJy/sL1w+Vcm7NQ0jhUIoY6kvtRwZUKzuZo1M=",
        "fingerprint": {
          "rawId": 593757326,
          "currentIndex": 1,
          "deviceIndexes": [
            0,
            1
          ]
        },
        "timestamp": "1663592290483"
      },
      "AAAAAKPP": {
        "keyData": "mJWsOXobyOMlZZZINjzJyPkf+W1xeQ3P5YJHHYFOAhs=",
        "fingerprint": {
          "rawId": 593757330,
          "currentIndex": 1,
          "deviceIndexes": [
            0,
            1
          ]
        },
        "timestamp": "1663639806539"
      },
      "AAAAAKO8": {
        "keyData": "agO+0pW4GZc8MAnA8+m8Jwem6Bu608lPI2gHbYfXtmc=",
        "fingerprint": {
          "rawId": 593757311,
          "currentIndex": 1,
          "deviceIndexes": [
            0,
            1
          ]
        },
        "timestamp": "0"
      },
      "AAAAAKO/": {
        "keyData": "rh2Z4LyacymFmyg6qM/OA+tnh7prmTfhH24hMOSLpo0=",
        "fingerprint": {
          "rawId": 593757315,
          "currentIndex": 1,
          "deviceIndexes": [
            0,
            1
          ]
        },
        "timestamp": "0"
      },
      "AAAAAKPI": {
        "keyData": "+ZTj5RvcRWNTzvDnpY3hwJO3DJFY4IADPuhxxQKhG04=",
        "fingerprint": {
          "rawId": 593757326,
          "currentIndex": 2,
          "deviceIndexes": [
            0,
            1
          ]
        },
        "timestamp": "1663599697646"
      },
      "AAAAAKPF": {
        "keyData": "EKZA9NJKEu0J7Pb1GUOmtOa7r8zzoNFgUuFJYzQ2PFk=",
        "fingerprint": {
          "rawId": 593757318,
          "currentIndex": 2,
          "deviceIndexes": [
            0,
            1
          ]
        },
        "timestamp": "1663586656087"
      },
      "AAAAAKO+": {
        "keyData": "JVQOdg3DH+Qa+fpgSoe+HaCkwSadKi75/45B5POn3+s=",
        "fingerprint": {
          "rawId": 593757314,
          "currentIndex": 1,
          "deviceIndexes": [
            0
          ]
        },
        "timestamp": "1663049911952"
      },
      "AAAAAKPA": {
        "keyData": "n+Xio9zRAB00jp1y/sKY/O8SSXaV/HHQVBfk6BXVa5c=",
        "fingerprint": {
          "rawId": 593757315,
          "currentIndex": 2,
          "deviceIndexes": [
            0,
            2
          ]
        },
        "timestamp": "1663503943596"
      },
      "AAAAAKPJ": {
        "keyData": "qK0r/ONlyH6hNRMsei06oKpHToR91LPgS1/t1vpg0p4=",
        "fingerprint": {
          "rawId": 593757328,
          "currentIndex": 1,
          "deviceIndexes": [
            0,
            1
          ]
        },
        "timestamp": "1663600386473"
      },
      "AAAAAKPQ": {
        "keyData": "aHR8VUFfnv8x7X3bx2yPL4erO7uv434IwcgNIZNSXnU=",
        "fingerprint": {
          "rawId": 593757334,
          "currentIndex": 1,
          "deviceIndexes": [
            0
          ]
        },
        "timestamp": "1663640258666"
      },
      "AAAAAKPL": {
        "keyData": "6IOq6mf1xYelUTFkx7BFwDIPw3Qi0zKHlloqhURxRLs=",
        "fingerprint": {
          "rawId": 593757328,
          "currentIndex": 2,
          "deviceIndexes": [
            0,
            1,
            2
          ]
        },
        "timestamp": "1663631706487"
      },
      "AAAAAKPE": {
        "keyData": "iPDrS04vQXqRCjXm8XzGW1VPa5EmnxiNxZjFbjphWKs=",
        "fingerprint": {
          "rawId": 593757317,
          "currentIndex": 2,
          "deviceIndexes": [
            0,
            1
          ]
        },
        "timestamp": "1663577466737"
      },
      "AAAAAKPG": {
        "keyData": "PPt2J8RQuZLpsqZKzIOKTU5HwDr/HLMAFqNelu+MgTM=",
        "fingerprint": {
          "rawId": 593757320,
          "currentIndex": 1,
          "deviceIndexes": [
            0
          ]
        },
        "timestamp": "1663586690404"
      },
      "AAAAAKPM": {
        "keyData": "EE1qvb6CDtQurUynZSX1GuwMVCTeQcRJIfqP2BE9kn4=",
        "fingerprint": {
          "rawId": 593757328,
          "currentIndex": 2,
          "deviceIndexes": [
            0,
            2
          ]
        },
        "timestamp": "1663634242741"
      },
      "AAAAAKPB": {
        "keyData": "w5zSIJbGAaMSRFkuaADYHb7k88y0r0IAcOqJnwIyZ2s=",
        "fingerprint": {
          "rawId": 593757315,
          "currentIndex": 3,
          "deviceIndexes": [
            0,
            2
          ]
        },
        "timestamp": "0"
      },
      "AAAAAKPN": {
        "keyData": "k7Skaj/U7E/OSm4JNjsfJJRFf/wwc3PjFzT2IVWzf6g=",
        "fingerprint": {
          "rawId": 593757329,
          "currentIndex": 1,
          "deviceIndexes": [
            0,
            1
          ]
        },
        "timestamp": "1663638300546"
      },
      "AAAAAKPC": {
        "keyData": "1HNxurPPa0c9X9EZwffvaECmpttaD4eKZEgdyboWnyE=",
        "fingerprint": {
          "rawId": 593757315,
          "currentIndex": 4,
          "deviceIndexes": [
            0,
            2
          ]
        },
        "timestamp": "1663539318047"
      },
      "AAAAAKPO": {
        "keyData": "uELQE0AqV4D6t4sM+LIu6W+0cbzzmRGVvwfu5MR5Slk=",
        "fingerprint": {
          "rawId": 593757329,
          "currentIndex": 1,
          "deviceIndexes": [
            0
          ]
        },
        "timestamp": "1663638355082"
      },
      "AAAAAKO9": {
        "keyData": "hFHmFLOa0fh2neWESXqtUXejqZeEardb/Z5wv/SeULM=",
        "fingerprint": {
          "rawId": 593757312,
          "currentIndex": 1,
          "deviceIndexes": [
            0,
            1
          ]
        },
        "timestamp": "0"
      }
    },
    "appStateVersions": {
      "critical_block": {
        "version": 14,
        "hash": {
          "type": "Buffer",
          "data": "P54PUDZ6HMZ4kj7XD87IxxkkZRLhCnSEpJC3Uytd7L+y5R/e75WEzIUnb4q8XBoue7ahVRd0szFC4ZubpG0bbJwwA5ifEZQfurCFQeAoIdEuoq19k1gqIgEsgcQb6SthiM78l7oQbnbSt3dbjm7ujSBotsUjgO32wlw3FcaYeu8="
        },
        "indexValueMap": {
          "9f4mAuMGkarrd8A3/WpY+O1e+XWYLvwRuvmXTPod9yY=": {
            "valueMac": {
              "type": "Buffer",
              "data": "V2nFACOMmN8GavBkIcsM1Hcad/7NtZB+DIHr4Wo4D/8="
            }
          },
          "meNZ0GQ3+ZxBTn23TJdhgNcS9maFCp0SiVEpdcL2auA=": {
            "valueMac": {
              "type": "Buffer",
              "data": "XbVoS/R9iefUrDjohLx4/0adl7XFj2iOk8KrY+Na0aI="
            }
          },
          "eq4HcoJScHKY0wPpGvdSq8ObEt9SSV2qA/WQy+b0WLA=": {
            "valueMac": {
              "type": "Buffer",
              "data": "R8IkOE5pHJRZ4d984jSYQr/n/SsuHkh1SK/Dn8NA6WI="
            }
          }
        }
      },
      "regular": {
        "version": 15,
        "hash": {
          "type": "Buffer",
          "data": "/JcDUrbk6Ey7zismcYS8Ou6GWBTOzJs8EL7NyBFz+T9NYk57W+8aMazh2JnQb/+LIBIgYB66CyPzegjxZdZz5z8tr4FKxWrrJJGCsF5O1l+IjYMIZspsuoGJPzvURJQ+UebPxEV+fbm1v6Qw4EjXfkJmVNF2YQSjvmkHAZRK6Hc="
        },
        "indexValueMap": {
          "v0a/CIZvoO/hx+xX4NPOjnZjCb1oGjQye9zNfGyeemQ=": {
            "valueMac": {
              "type": "Buffer",
              "data": "KZqQEmOrJ64pkqc/sgI676cmdxjJSzT40ncp++QTFzY="
            }
          },
          "lb3dbbC53LcDT6x9JMPEGrnLrx2CQ535F4bV/qwvJtk=": {
            "valueMac": {
              "type": "Buffer",
              "data": "rVffOqBA6XLaGzRiv2weIMEIRiAvlcRlGFmggYo9DDg="
            }
          }
        }
      },
      "regular_high": {
        "version": 42,
        "hash": {
          "type": "Buffer",
          "data": "dIK+3oViadNQA0FnWzywsdG65TfXgrDtoW0gAUBOU84fWVvuRfslBk4HfoQBzzPljCur+/9uxlvy8YrpuNtM1SjfufIRWBVTB10r4po1PIsV6AiJ/V8z9VzMnk4U+tx0CFufZ1QVw6vTlL2vvTLU23PunclPso5rUBG6beolDhI="
        },
        "indexValueMap": {
          "CdRFNjZU1fJj9+i/tlb7ygu9uQ5fR9e5O+p7vSR6SVs=": {
            "valueMac": {
              "type": "Buffer",
              "data": "4KNWc6uyarQBzdp+QSk93kB5oF7XKRdUp8rKYlCEkR8="
            }
          },
          "DW7DY8hSoBN02CSaS0prlmdttI+A890zwftMrj+OT8A=": {
            "valueMac": {
              "type": "Buffer",
              "data": "4vJWWg36UByFk2jqmpcaPYKJQlyAUa9vzhdmzxeDig0="
            }
          },
          "Ghuy1bbfoq/GwIS4hKOESeJvw840suP+3kQ+TjjEvzo=": {
            "valueMac": {
              "type": "Buffer",
              "data": "moXevbk+DGaKmT59oV1ZlG7mYVX5FuFMA6Ari4FnXGQ="
            }
          },
          "keltH9xHHATisNJGNp4V7q3Q+hvPF5AEqYp6dBt7n7o=": {
            "valueMac": {
              "type": "Buffer",
              "data": "mx7dNSHg5HhNiD76hgs+W4ON+NqIGqmDNfgGXDLb5eQ="
            }
          },
          "rqy4SsCAeMjVPHPB6wHqc6qZ1K6w85uo9mPKAYGbDUg=": {
            "valueMac": {
              "type": "Buffer",
              "data": "L3rRL9TIvy50TNThlnLllXsfqz8QrgbtahsLIyYLEZY="
            }
          },
          "sbMdlPmns6QGykbPURzdrAS39fchoHDdEUPun0VQg7Y=": {
            "valueMac": {
              "type": "Buffer",
              "data": "uR98HTiOI5G6MrcdgzDMr8iYAVC4qijSRM4qqIO4aJo="
            }
          },
          "ytmw9jOUPCRa2FYxgWCibDtShsci5OXK38TZ1E/2wco=": {
            "valueMac": {
              "type": "Buffer",
              "data": "VZnVq7rrE2pt+vy5qCwUTnRsKu1XOrH32j5rBmepPU4="
            }
          },
          "4q0LWFb+0JNH94oPOe6BeAdGrsHOthvaAQoH720k9eE=": {
            "valueMac": {
              "type": "Buffer",
              "data": "mR88U+TZd1QPUZeMkly6meyO68TyNGawY9mLiQ84kX8="
            }
          },
          "cwVH6OMwMtS5S/34WuKYoKxkg8u0qBsD+FJzyGK1yNs=": {
            "valueMac": {
              "type": "Buffer",
              "data": "ccprLfdgIP6zR52/DutLGsOVPFNyvnuXKRLYggKlpyQ="
            }
          },
          "NYY9+XxwGj64XgP619/8ZHZ4VlOa2hr+NIf9u56W/EI=": {
            "valueMac": {
              "type": "Buffer",
              "data": "bX6X8MkZ5p5J7dxdW2fg/uDyjRytgO+S4vSD/J+iu0U="
            }
          },
          "z5EmSLgXlmjXL8BuWdEdco93+daBaLbp9GhBIz79UN8=": {
            "valueMac": {
              "type": "Buffer",
              "data": "cXlxneqoo4SnqdJN0J5xQ+CBl5mTVyLdWe622bdfqVE="
            }
          },
          "ifPf8q1urJ48vyxLijo/T/OVVdkzkqJpJgdUu51HkIk=": {
            "valueMac": {
              "type": "Buffer",
              "data": "BjMKCBWJyXGVpPi5eu/HuCWFUOTj+g9qIztCwUAUCc8="
            }
          },
          "hvQZngHMyapW7oKOEdRCkKYnEwh6obpuzaLJZH8QJO0=": {
            "valueMac": {
              "type": "Buffer",
              "data": "2l0mCgsRfoKsAt94rk+XggrjXyxM4Ai+NoBp09aDgHI="
            }
          },
          "e9YgRY64h9+chQO0k60YgmIOPEa9mBQiBmdEDb58fAA=": {
            "valueMac": {
              "type": "Buffer",
              "data": "zn5uNIHzD/OmPFsSlhvGyfqd1nA0auJz2dpn6ne5Zuo="
            }
          },
          "mZbXh67mpJgruLpVelkZ5r7xZIlKbHBwV6JRHDCJ8t4=": {
            "valueMac": {
              "type": "Buffer",
              "data": "dXIhon7YoUVYMD9fD93QM1+snQpqdK37V8AUjRGL+5Q="
            }
          },
          "QbCTotrHQFKIv0vvFVlZs4dQkg0Q2azK3k4whpzUkQ4=": {
            "valueMac": {
              "type": "Buffer",
              "data": "6f1iTlCnwNBHC2K1mci0uTyyInLCGWpzTYST2laq69A="
            }
          },
          "9JtzFNW8my/92cOxikoZRA5tIPo1jrf1Dz6WXxXlOHA=": {
            "valueMac": {
              "type": "Buffer",
              "data": "dLLCOEgVouK/Z2VyasYa31sM2/7r+YKwND4nSK7pyNU="
            }
          },
          "JTeAk7jaUgQVFoO5utq6PL+X4lREQHHYfNbvNMsjl0A=": {
            "valueMac": {
              "type": "Buffer",
              "data": "n/OStvVxPIs3S7gkgkQboyRI1yauJkBEm7cEMixs9Yw="
            }
          },
          "7x75WIXXGa4UioFINKC/MHyrKSyIMDiOzaJxCf0nFuU=": {
            "valueMac": {
              "type": "Buffer",
              "data": "GiGEcSB+RXqVIrPyZDxYQ7G7/ZDHd8lYqSzYRlhMOkc="
            }
          },
          "3WYjTovT8cxUOME5qxIinDqz2ubT4/8Bgpfs3s84Ph8=": {
            "valueMac": {
              "type": "Buffer",
              "data": "e6TTwrxUkiU9iZTA41N2W7L/W1E7Reb9hAiXFk+WaSw="
            }
          },
          "FNKRWKpDIaAfZ5wYpF0g/fWUxLg1bGx6ZDS/S/Uvj1I=": {
            "valueMac": {
              "type": "Buffer",
              "data": "JNBRBB7RVHmWEqmMek6Xu4gyeDAR1jBJckX+XQ+NAOw="
            }
          },
          "qWNvflQGxUklkXwnu70qdH1UAFz9epbF1nEIryWcMM8=": {
            "valueMac": {
              "type": "Buffer",
              "data": "n4ynJOAWciSBklJbBaxK7vaZeOsxHW4hecSetZkFgIQ="
            }
          },
          "eWbx+tQzS8f3530+H3pEgJfJrL/tPVtZgsJQ+74/UjE=": {
            "valueMac": {
              "type": "Buffer",
              "data": "O66fAYd17MPGjlw4jT1vQGx3zw2Sho1vIFK63jhpUiE="
            }
          },
          "9y1UsqfhxubSUfmp9VH5aXB8M81QEc0riUXOCwg3vu8=": {
            "valueMac": {
              "type": "Buffer",
              "data": "/p7ZRCRxiBPlIkKN6UNohYYTUJaUKz2jSnc4HI/kyXE="
            }
          },
          "tgcd7B5SzrvIR/Z0faz9iPWDca3ROR2kFk1bCimzXEg=": {
            "valueMac": {
              "type": "Buffer",
              "data": "Ey6hjyElsUFMVDD4Y4UATDpEn9TU672rSZrFHYrx2po="
            }
          }
        }
      },
      "critical_unblock_low": {
        "version": 31,
        "hash": {
          "type": "Buffer",
          "data": "6xlEx5duSytAonP6WuzQW6j4c7bK6VocHlc6XrZVJeX3nBscSGK3y/Q0W4AZmP5Li3t0Gng1jIAHZq5ji/G3qtCdvPkVIeZ3w6jdFWnrKVrOyI7JO3o76+teDFl6XGjEmM41HRpwiLV508jwnJIY1m+G0oh5btmL4fKWuHCM2wc="
        },
        "indexValueMap": {
          "CI3TWgEHizkksnxhaE16rTnIiNf36Z2jlBmA0vJXX08=": {
            "valueMac": {
              "type": "Buffer",
              "data": "Jr2l8YCCA4FxpSfLaguD9bGHxK/+SpWuH7gcsq+NSGg="
            }
          },
          "CarOb8GER4/BoL8NRzVhFNidrbLYbFAJgN5bbF/1oa4=": {
            "valueMac": {
              "type": "Buffer",
              "data": "UxzI48EO9y/vtd1cz34p8yhqZ1IDUwjqlot4prQIcHQ="
            }
          },
          "D+Z5CzczBGjd/cWvTKJUNGv5JeuA/N3kHgTOOE4xWuw=": {
            "valueMac": {
              "type": "Buffer",
              "data": "4qmhh0jrrv5tZ0JI6cAmNgAX8oJ8+OqpVEoNQbmzFBk="
            }
          },
          "HkJbgdGmZ9ASoYD1AaYfi7dQkEDe/TCpZoXYXM+h9Nc=": {
            "valueMac": {
              "type": "Buffer",
              "data": "sfG7N31lc09/Yfgkup4FMzH9Kuw/qeyvitM+EWVPO04="
            }
          },
          "IlJKxDo1dVFzUBjrbYJHWxZTPQw3UNWiqCXocmG7TLY=": {
            "valueMac": {
              "type": "Buffer",
              "data": "0XyGhJfNS1kHkhTlXbllFReXXeduSbosnL5b1J2sLs8="
            }
          },
          "Kn8X+hKSgDgJgzjswQxCsB1v0uUurSx/9ckiLLA7Zz0=": {
            "valueMac": {
              "type": "Buffer",
              "data": "opaxDjy6r3A7NMAguFg1+n7AaTO0KJ5cGP5Rb8PV2BA="
            }
          },
          "M7SjJJ/Hl03IaZO3Uflw5rMj8vjZgEKUtXV/mZ9kKVA=": {
            "valueMac": {
              "type": "Buffer",
              "data": "+J+UTIJWJmdOUMxLpQ/VtSgizWxmcRKEsZcfcN/9Juk="
            }
          },
          "OYemk31jQVMZCrGDOiOVWNjToenGEaJ7x2lhlnpK15s=": {
            "valueMac": {
              "type": "Buffer",
              "data": "Hr4WgDJdQkhkCD5xlZye55AYAzLPgei9L4XMcrGMtSA="
            }
          },
          "Pk9epvH0BkXRdM9GFHOW+eBJ01UnJXwFNHcbxQWJXEs=": {
            "valueMac": {
              "type": "Buffer",
              "data": "T4D+cqt3uDjxLCR5voC2FynfKZL1WWEB+zhI2exSabc="
            }
          },
          "Um/Lb+VIXWC8wDyMm4jSXb/DYSqBe4Tr6+d5w4vWYpE=": {
            "valueMac": {
              "type": "Buffer",
              "data": "sMzjtiZ1mM6a5+veRQgcL05zOYs3Eu+BgVy5vhLQ3QQ="
            }
          },
          "U8UN1ZlJTMDLvXZZLcKoz8oVYu74ssxQEtxJVhAlVxg=": {
            "valueMac": {
              "type": "Buffer",
              "data": "xCAmvxBrWni4zewzqA9uIn2xgf3pU3IFl56kJngp7+8="
            }
          },
          "VW+YxYH3xJzl9bv4Qo/1wpsB8WNKxOJ9r1iFAcUi8qg=": {
            "valueMac": {
              "type": "Buffer",
              "data": "AmySh3NJ8vp49PD//twI/WqR2qDrb2NvVG+gHVDhZ/A="
            }
          },
          "WPjrcc4hRO8DflZC/7kDuCVzhBB6dew4u8fyDufrW+w=": {
            "valueMac": {
              "type": "Buffer",
              "data": "ekdEFRWLM65zXYF421YSN92/C98ZJ6nAW5QnDyEuRU0="
            }
          },
          "cHM5zJS5FT9SxuyFLUFiX19gso109ZSAChqSNhSmF5Y=": {
            "valueMac": {
              "type": "Buffer",
              "data": "rJaynceQT17GTwcyZ67/k9/iK3COy1zjOq8fzFqrjV4="
            }
          },
          "hVDtAMu2doEn6R3CeC5CcFYAdjBGi/MtQPNcDSH++cQ=": {
            "valueMac": {
              "type": "Buffer",
              "data": "U4GD2KPJiI3zxyB0Qmb0lIfE/DIRfDQicm/ELSlKWXY="
            }
          },
          "htE1fvxCWyzBQtQXBqhwX2ka7pmTsbvhc0njEiLNa0k=": {
            "valueMac": {
              "type": "Buffer",
              "data": "Ngb4/Gjyt0PzHUHS86/mESRqcQZsOql2xZu1iSmka5E="
            }
          },
          "mXCJ3G45UvZtODoofewY5q43uvw/V3yvX1xTDkP8RAk=": {
            "valueMac": {
              "type": "Buffer",
              "data": "JVoCfC+rdi1jMIe1FgO09CBk+T/7mewp1SehDHDaTtY="
            }
          },
          "nLl+KSKKkOL3rqUqziwloo67N+/LDtBcddZOlHSCVag=": {
            "valueMac": {
              "type": "Buffer",
              "data": "LRi7h+rl5wZ0u92uGkt8ILkl+SNoATsTeB3eD3VvS/Q="
            }
          },
          "1QOdZeMKKANn8OAhvLCI6nqvGSxKCSNRDn9n57jh710=": {
            "valueMac": {
              "type": "Buffer",
              "data": "QsoHmtlIlXU+qQxVXf3yLNUxGBnWVKjL+4BALdaQ6Do="
            }
          },
          "7MkaiuSAKA+YCUcxrMukluNocl5bHobfIlCosDRzMcw=": {
            "valueMac": {
              "type": "Buffer",
              "data": "nflVGNAAR0DKgAISNsRzxqpS4yCHW/czKYaXt91kkKw="
            }
          },
          "IRRdgQNaauExGo45PuQAoQ1L13uXK/HSm7MZQrOiwUs=": {
            "valueMac": {
              "type": "Buffer",
              "data": "wLtQy+p3jMcxdNcQAUz8WWAmc/eJRicb/HX42iPVr6s="
            }
          },
          "6+ro+xwAX+QHCH0Gx8/+bmSdroRQKjqP9ZQ5CV+ZVX8=": {
            "valueMac": {
              "type": "Buffer",
              "data": "QhHLdJwOh4Q6J27CwVIs/JUpF6zSsduu5Hzy7DorOBo="
            }
          },
          "C9YRhE5cpBuhNCP5lKoLUoaSabTqNETnqkTIgK0A0G8=": {
            "valueMac": {
              "type": "Buffer",
              "data": "obqExWuc/SdzHTa5Z8g9t6u+AWGvxuJlpBiISvoERKI="
            }
          },
          "cFiRRcNBUBCizL29altTWFFkBHKpqpYcolRcPnCUG8k=": {
            "valueMac": {
              "type": "Buffer",
              "data": "NjXp6z+GhMoXdkEotM+hXkp8l7iUGVf6OfEdkf8BlYE="
            }
          },
          "clvktU3RVKdHraZmzoRFP2yfoasl2XEqzH7CPElecc0=": {
            "valueMac": {
              "type": "Buffer",
              "data": "o6QS5HJzMalBMcRj4xWcQhFOmYbO4XppAzLkQ1Swy/k="
            }
          },
          "9hsRsCuF7Q+CHGH/yvH0G03m/jjBjlzTVbXNYJnGDYk=": {
            "valueMac": {
              "type": "Buffer",
              "data": "3aQvQrIM2QwVMVlGnWFK24ey/Fb7hGvVlBU4e3EZmQQ="
            }
          },
          "wcrDpwSZ8Klh/kl2UxuoTF4ZOklOh/O28IiM1LgQxtY=": {
            "valueMac": {
              "type": "Buffer",
              "data": "XrVhL4IIyga5OWr0BN1HkEq/b42vAqIaoSn64KjF0BU="
            }
          }
        }
      },
      "regular_low": {
        "version": 33,
        "hash": {
          "type": "Buffer",
          "data": "RLoBcZRBDrgb4+Pp96gUwePicJuFQW0KusFI7Y4oPgXtf/cg/fr7wBN3Hu5/QhQefUIIen+QBOwVxNT9wyRVpY36NiGL5Mbv/xe3zolySq/QNoxioR2TUGRRB8M2QUeHO4OgbqaUbq0iQ0buvRfLj5cz/YMYi0/fGaGtlTZCLNA="
        },
        "indexValueMap": {
          "BRqd9qYFnZkY2Sq6XV+AxynVFw7QhicZMTmhruw++2o=": {
            "valueMac": {
              "type": "Buffer",
              "data": "6W078YY/lq5t3jYNkJEJkt4P+T+rRbZSKBd3apL0REw="
            }
          },
          "FUSyn/JTTuoN8IHRV/IIOtZmDeITcTYGWbiEFyXvbiU=": {
            "valueMac": {
              "type": "Buffer",
              "data": "Yu+BQCXFAKWFWgN3lon5df3y4bBOs3GAedpOhsxKb98="
            }
          },
          "MhS/8Ct9Wnp/S53lLboM4Z1awCcZbNLIwncI7LSITqU=": {
            "valueMac": {
              "type": "Buffer",
              "data": "gtrs+SrKak/wd9f6NJS6P0F8Aez1ie2LjEkoU3hZgjQ="
            }
          },
          "UZci7ZdAZXv6dhkDzJrqQgX0/8tGNFFW2BIrpNr8Dx0=": {
            "valueMac": {
              "type": "Buffer",
              "data": "/ro6XiTFDQISNC5c0TBAc1B3EqKRr7j5FRVVT4Ntfr4="
            }
          },
          "ZjVile9NMTUZNzMA6VAQXKG+IDno0gw0dfr8VDg5c/g=": {
            "valueMac": {
              "type": "Buffer",
              "data": "1fgOeMEIAfYbkF6q15dgsYplybjgbKKqKBf4RklSthA="
            }
          },
          "epIdiq/oUWPfjx0Ff+F+snlFulynKc5bDppXwyoMJK4=": {
            "valueMac": {
              "type": "Buffer",
              "data": "IS1KgFnMhwF1LMb1qbShl9RaysbjMM2Cznne4Yp+u7A="
            }
          },
          "e8PRoce+ldLeWU8ZlC64XjIs2Ex9MOjexMcsEUzn3RU=": {
            "valueMac": {
              "type": "Buffer",
              "data": "AArtX8fR3dDOOpIao5pOXxGXCht5UnAR4jaHmHNrqB4="
            }
          },
          "pPHpO43Mg95lbcBasdU/hNp6qW5ena80FJ1EBvgSA78=": {
            "valueMac": {
              "type": "Buffer",
              "data": "BElQmVkei7KAc+cdkJeg0Ookqbn6PjLsiY96KGT8c/o="
            }
          },
          "qrKLxy5s5r4SsSF9SSViwo3KsXg3VusCCdtdtaFEFac=": {
            "valueMac": {
              "type": "Buffer",
              "data": "1v2FUPo8yIV2WD4oDn9wABGtuvMs1BYEMpi0Bo78iWk="
            }
          },
          "wEyrF//bpCflRlcHxxn0w1hHUOzzvPhmWqtlT0EDBiY=": {
            "valueMac": {
              "type": "Buffer",
              "data": "uHgrY/vYccoCJuWGWV7BaxNheBO6RZs8Y6L1Ywo7Xo4="
            }
          },
          "xyNJBSeU0l1MwM+c/NlkZ5TOMcKr6SesxKJUXb71Qs0=": {
            "valueMac": {
              "type": "Buffer",
              "data": "UCpTL3Hhld0sKNtQ+s4mlfdIU+P17YAKBDPJT9RQQ0U="
            }
          },
          "yZlX14c5HbVw5VoV70kiua3LBzxtDX2FVj8LBqVSETM=": {
            "valueMac": {
              "type": "Buffer",
              "data": "LlnVRWbhH1ZvA1CJul52fJ3wOSXx0QuWODSoGb9wvxw="
            }
          },
          "0vIqksJiHVGcEd/MEensItSga/oSRC2M21IZ2BvHm9k=": {
            "valueMac": {
              "type": "Buffer",
              "data": "bFqX9Y2REwZN4M1Rl35HQ9/yceyMQM+AI3tGP5m3eTc="
            }
          },
          "4tS4UBd97GJj+ayGAO4KHLQjwpm5BYnIBjfRFZV0QgU=": {
            "valueMac": {
              "type": "Buffer",
              "data": "H5Ts2AZK2EzcdPIy0I3Ge5zjotn9Jo2wuZvsY4rZf8s="
            }
          },
          "41+Thi/ouwmebiD+gBzoGZ5o56Wc2fyZRpEuqLSxOAg=": {
            "valueMac": {
              "type": "Buffer",
              "data": "QTKhzB0uYcgFQ6lZ7jtdw44jeRCW6rdlTCjU5keVjXk="
            }
          },
          "5EhRxDLvZhqK9gLHUB5uZh+ZI3Grh+f0hi/Ne9xJqhw=": {
            "valueMac": {
              "type": "Buffer",
              "data": "3c8kHkOc/5cJ7RxqwGawY8IpAYNQGuKgtTz25+sB7t0="
            }
          },
          "Yx4we8xWRhaJr2DhG25eez1z0jz878EiyPiNDkSej4A=": {
            "valueMac": {
              "type": "Buffer",
              "data": "y3CM7JF8j9SvD6EzGkwno+Br798MJiwrS/zS4ye+Tcw="
            }
          },
          "d0wTZRHtOXUHvhUrQqVuJga2UxqvGcxaza1kH6LG7TA=": {
            "valueMac": {
              "type": "Buffer",
              "data": "NUTjsOP5+yYoC+azK8r6kG1j1fX/xS0msjj+PrK31Vc="
            }
          },
          "ciIwdUkl5YluI3Xo46WPehySCGTPlhJqFF0IQdcFgn0=": {
            "valueMac": {
              "type": "Buffer",
              "data": "qlaBavXxlIQq6EL+Jb+qJzZeg5CdV5upm15q5zJiDbY="
            }
          },
          "ahcmgN1YbN3tQjRq8rRW7A/4lJavKLr7UEVTeZxelOY=": {
            "valueMac": {
              "type": "Buffer",
              "data": "seynCFjrWtH4y4yOpSiVJjThyap7NUXZtdJ9wffj9iw="
            }
          },
          "fia6XcA43ZWIDWBIjPRFoM38DVmTrz4OXrursCXO3T0=": {
            "valueMac": {
              "type": "Buffer",
              "data": "TyKhBhuh4izP9Xe19TmvSL6bLMwXKYXJiaeWKe5DUzE="
            }
          },
          "+SL6F9xZQItsZxogmkypWnAwswE7VWm846M9fovbx/E=": {
            "valueMac": {
              "type": "Buffer",
              "data": "iYo9EukL2jAPLbaEjDhgeaBedqnsGF7wIfTt4z+RfwY="
            }
          },
          "9XGDLGPWE1tTJYH2cdsta9V8T389CR/spnzuFPTLoHo=": {
            "valueMac": {
              "type": "Buffer",
              "data": "eNl5+iLggJlhsboB7Cj2dgpItsVWR97Vz9nJqD7kslE="
            }
          },
          "rQiYgJnQAl1EG8goYxlE8LVwNQNaM9204tn/yMASGIU=": {
            "valueMac": {
              "type": "Buffer",
              "data": "jnXGj/GVmAjlGdhQRMD3+fFb/bm100TzIOs7uBZJdBE="
            }
          },
          "5VDqwFh2irQu8+2SSVONTElPW0spSZ4JWBnzXQFyiM0=": {
            "valueMac": {
              "type": "Buffer",
              "data": "s132WJlTF4LKQpcpo1DXF+nF41Z9L84qdKk4QGztG2w="
            }
          },
          "uUDVSLKlsJhGnwwfGvwI42ix/JWLNe3ytqU9c3T8W3c=": {
            "valueMac": {
              "type": "Buffer",
              "data": "PUF/Mynby5nZ3xUBj/9Azfv5QayDZtBWmTvlKXE76ww="
            }
          },
          "eTYfGWKKv8hgXslWDdjRtsMoyPXcw6An600nCVDRAQM=": {
            "valueMac": {
              "type": "Buffer",
              "data": "zoVTQyYZ9ATjmz72qwFjSyEKgDHN1uFRB42ofZQn7UI="
            }
          },
          "Oeh8LQwYvkHphW0MOwle1qH7Qc6pRCUYIG2nKnWotLk=": {
            "valueMac": {
              "type": "Buffer",
              "data": "4JUEtOXmylm7z8ensz4sYDPYGOFkQrw3Zln1ahcTctw="
            }
          },
          "yco3QmgxIs5jpMf5eP5GPfZVbfz3Jdc8g2WOf4PCJBw=": {
            "valueMac": {
              "type": "Buffer",
              "data": "wja/N+TyuiGpJPEy/zjHuXbXYCA/Aqs6lPGMLvwaiXk="
            }
          },
          "ua1OSC+DAoFi5B3r1YCiJsyN0bivOb0R39+QLpPph/s=": {
            "valueMac": {
              "type": "Buffer",
              "data": "0k0f5jim3Q8tm2AVvxukaZ/CnCuiQe0Zx5bqXFRLBDk="
            }
          }
        }
      }
    },
    "senderKeys": {
      "status@broadcast::62895382636517::0": [
        {
          "senderKeyId": 1299265448,
          "senderChainKey": {
            "iteration": 3,
            "seed": "GlHnhu+xe6ECD8w9k172E/uO0nEu1kLXWcXmw6uGs0o="
          },
          "senderSigningKey": {
            "public": "Ba5wY803Gp5vjG+laXGyupJKDTUQ6cSHioqILOB2S7sV"
          }
        }
      ]
    }
  }
}